cppe5/__init__.py
cppe5/download.py
cppe5/download_tfrecords.py
cppe5/tensorflow.py
cppe5/torch.py
cppe5/version.py
cppe5-0.1.1.dist-info/LICENSE
cppe5-0.1.1.dist-info/METADATA
cppe5-0.1.1.dist-info/WHEEL
cppe5-0.1.1.dist-info/top_level.txt
cppe5-0.1.1.dist-info/RECORD
